topsis_Urvi_102203720/__init__.py
topsis_Urvi_102203720/topsis.py
topsis_urvi_102203720-0.1.0.dist-info/METADATA
topsis_urvi_102203720-0.1.0.dist-info/WHEEL
topsis_urvi_102203720-0.1.0.dist-info/licenses/LICENSE
topsis_urvi_102203720-0.1.0.dist-info/RECORD
