Metadata-Version: 2.4
Name: topsis-Urvi-102203720
Version: 0.1.0
Summary: A Python package for TOPSIS implementation
Project-URL: Homepage, https://github.com/UrviGarg/102203720_topsis
Author-email: Urvi Garg <urvigarg43@gmail.com>
License: For `LICENSE` (MIT License):
License-File: LICENSE
Classifier: Development Status :: 5 - Production/Stable
Classifier: Intended Audience :: Developers
Classifier: License :: OSI Approved :: MIT License
Classifier: Operating System :: OS Independent
Classifier: Programming Language :: Python :: 3
Requires-Python: >=3.7
Requires-Dist: numpy
Requires-Dist: pandas
